intercom/__init__.py
intercom/admins/__init__.py
intercom/admins/client.py
intercom/admins/raw_client.py
intercom/admins/types/__init__.py
intercom/admins/types/admin.py
intercom/admins/types/admin_avatar.py
intercom/ai_agent/__init__.py
intercom/ai_agent/types/__init__.py
intercom/ai_agent/types/ai_agent.py
intercom/ai_agent/types/ai_agent_last_answer_type.py
intercom/ai_agent/types/ai_agent_resolution_state.py
intercom/ai_agent/types/ai_agent_source_type.py
intercom/ai_content/__init__.py
intercom/ai_content/client.py
intercom/ai_content/raw_client.py
intercom/ai_content/types/__init__.py
intercom/ai_content/types/content_import_source.py
intercom/ai_content/types/content_import_source_status.py
intercom/ai_content/types/content_import_source_sync_behavior.py
intercom/ai_content/types/content_import_sources_list.py
intercom/ai_content/types/create_content_import_source_request_status.py
intercom/ai_content/types/external_page.py
intercom/ai_content/types/external_pages_list.py
intercom/ai_content/types/update_content_import_source_request_status.py
intercom/ai_content/types/update_content_import_source_request_sync_behavior.py
intercom/ai_content_source/__init__.py
intercom/ai_content_source/types/__init__.py
intercom/ai_content_source/types/content_source.py
intercom/articles/__init__.py
intercom/articles/client.py
intercom/articles/raw_client.py
intercom/articles/types/__init__.py
intercom/articles/types/article.py
intercom/articles/types/article_list_item.py
intercom/articles/types/article_list_item_state.py
intercom/articles/types/article_search_highlights.py
intercom/articles/types/article_search_highlights_highlighted_summary_item_item.py
intercom/articles/types/article_search_highlights_highlighted_summary_item_item_type.py
intercom/articles/types/article_search_highlights_highlighted_title_item.py
intercom/articles/types/article_search_highlights_highlighted_title_item_type.py
intercom/articles/types/article_search_response.py
python_intercom-5.0.1.dist-info/METADATA
python_intercom-5.0.1.dist-info/WHEEL
python_intercom-5.0.1.dist-info/RECORD
